hardware/igcn_accelerator.sv
//=====================================================================
// igcn_accelerator.sv  -- Icarus-compatible, fixed (final)
//=====================================================================
`timescale 1ns / 1ps

module igcn_accelerator #(
    parameter integer NUM_PES = 4,
    parameter integer C_MAX = 32,
    parameter integer PE_COMPUTE_CYCLES = 100,
    parameter integer FRAGMENTATION_PENALTY_CYCLES = 50
)(
    input  wire clk,
    input  wire rst_n,
    input  wire start_processing,         // 1-cycle pulse
    input  wire [15:0] island_size,
    input  wire strategy_is_enhanced,
    input  wire island_needs_penalty,
    output wire island_accepted,          // registered 1-cycle pulse
    output wire accelerator_busy,
    output wire processing_done
);

    // ----------------------------
    // Registers / state (module scope)
    // ----------------------------
    // PE state: bit per PE (0 = idle, 1 = busy)
    reg [NUM_PES-1:0] pe_state_q;
    reg [NUM_PES-1:0] pe_state_d;
    reg [15:0] pe_timer_q [0:NUM_PES-1];
    reg [15:0] pe_timer_d [0:NUM_PES-1];

    // controller FSM: 0 = idle, 1 = waiting
    reg controller_state_q;
    reg controller_state_d;

    // latched request info
    reg [15:0] latched_island_size;
    reg        latched_strategy;
    reg        latched_needs_penalty;

    // island accepted pulse (registered)
    reg island_accepted_q;
    reg island_accepted_d;

    // helper (module-scope temporaries to avoid mid-block declarations)
    integer i;
    integer pe_idx1;
    integer pe_idx2;
    integer pe_idx;
    integer cycles_to_run;
    integer cycles_to_run_l;

    // ----------------------------
    // Sequential: update PEs & controller latch/accept
    // ----------------------------
    always @(posedge clk or negedge rst_n) begin
        if (!rst_n) begin
            pe_state_q <= {NUM_PES{1'b0}}; // all idle
            for (i = 0; i < NUM_PES; i = i + 1) pe_timer_q[i] <= 16'h0;
            controller_state_q <= 1'b0;
            latched_island_size <= 16'h0;
            latched_strategy <= 1'b0;
            latched_needs_penalty <= 1'b0;
            island_accepted_q <= 1'b0;
        end else begin
            // update PE registers
            for (i = 0; i < NUM_PES; i = i + 1) begin
                pe_state_q[i] <= pe_state_d[i];
                pe_timer_q[i] <= pe_timer_d[i];
            end

            // controller state and registered accept
            controller_state_q <= controller_state_d;
            island_accepted_q <= island_accepted_d;

            // latch request when controller idle and TB asserts start_processing
            if (controller_state_q == 1'b0 && start_processing) begin
                latched_island_size <= island_size;
                latched_strategy <= strategy_is_enhanced;
                latched_needs_penalty <= island_needs_penalty;
            end
        end
    end

    // ----------------------------
    // Combinational next-state generation (single driver for pe_state_d / pe_timer_d)
    // ----------------------------
    always @(*) begin
        // default: copy current states / timers (with countdown behavior)
        for (i = 0; i < NUM_PES; i = i + 1) begin
            if (pe_state_q[i] == 1'b1) begin
                if (pe_timer_q[i] <= 1) begin
                    pe_state_d[i] = 1'b0; // idle next
                    pe_timer_d[i] = 16'h0;
                end else begin
                    pe_state_d[i] = 1'b1;
                    pe_timer_d[i] = pe_timer_q[i] - 1;
                end
            end else begin
                pe_state_d[i] = 1'b0;
                pe_timer_d[i] = 16'h0;
            end
        end

        // controller defaults
        controller_state_d = controller_state_q;
        island_accepted_d  = 1'b0;

        // choose active request: new if controller idle and start_processing, else latched
        if (controller_state_q == 1'b0 && start_processing) begin
            // compute cycles_to_run for live request
            cycles_to_run = PE_COMPUTE_CYCLES + (island_needs_penalty ? FRAGMENTATION_PENALTY_CYCLES : 0);

            // initialize sentinel indices
            pe_idx1 = -1;
            pe_idx2 = -1;
            pe_idx = -1;

            // try allocate pair if enhanced and fits 2*C_MAX
            if (strategy_is_enhanced && (island_size > C_MAX) && (island_size <= 2*C_MAX) && (NUM_PES >= 2)) begin
                // find contiguous idle pair
                pe_idx1 = -1;
                for (i = 0; i < NUM_PES - 1; i = i + 1) begin
                    if ((pe_state_q[i] == 1'b0) && (pe_state_q[i+1] == 1'b0) && (pe_idx1 == -1)) begin
                        pe_idx1 = i;
                        pe_idx2 = i + 1;
                    end
                end
                if (pe_idx1 != -1) begin
                    pe_state_d[pe_idx1] = 1'b1;
                    pe_timer_d[pe_idx1] = cycles_to_run;
                    pe_state_d[pe_idx2] = 1'b1;
                    pe_timer_d[pe_idx2] = cycles_to_run;
                    island_accepted_d = 1'b1; // allocated successfully
                    $display("[%0t] Controller: Allocated island size %0d to PE pair %0d-%0d (Enhanced). Penalty: %0d",
                             $time, island_size, pe_idx1, pe_idx2, island_needs_penalty);
                end
            end

            // fallback: single PE allocate if fits
            if (!island_accepted_d && (island_size <= C_MAX)) begin
                pe_idx = -1;
                for (i = 0; i < NUM_PES; i = i + 1) begin
                    if (pe_state_q[i] == 1'b0 && pe_idx == -1) begin
                        pe_idx = i;
                    end
                end
                if (pe_idx != -1) begin
                    pe_state_d[pe_idx] = 1'b1;
                    pe_timer_d[pe_idx] = cycles_to_run;
                    island_accepted_d = 1'b1;
                    $display("[%0t] Controller: Allocated island size %0d to PE %0d. Penalty: %0d",
                             $time, island_size, pe_idx, island_needs_penalty);
                end
            end

            // if still not allocated: either no free PE (wait) or too large (error -> unblock)
            if (!island_accepted_d) begin
                if ((strategy_is_enhanced && (island_size > 2*C_MAX)) || (!strategy_is_enhanced && (island_size > C_MAX))) begin
                    $display("[%0t] ERROR: island_size %0d too large for strategy. TB should partition it.", $time, island_size);
                    island_accepted_d = 1'b1; // unblock TB defensively
                end else begin
                    controller_state_d = 1'b1; // WAITING_FOR_PE
                end
            end else begin
                controller_state_d = 1'b0; // allocated -> stay idle
            end

        end else if (controller_state_q == 1'b1) begin
            // attempt allocation for latched request
            cycles_to_run_l = PE_COMPUTE_CYCLES + (latched_needs_penalty ? FRAGMENTATION_PENALTY_CYCLES : 0);

            pe_idx1 = -1; pe_idx2 = -1; pe_idx = -1;

            if (latched_strategy && (latched_island_size > C_MAX) && (latched_island_size <= 2*C_MAX) && (NUM_PES >= 2)) begin
                // find contiguous idle pair for latched request
                pe_idx1 = -1;
                for (i = 0; i < NUM_PES - 1; i = i + 1) begin
                    if ((pe_state_q[i] == 1'b0) && (pe_state_q[i+1] == 1'b0) && (pe_idx1 == -1)) begin
                        pe_idx1 = i;
                        pe_idx2 = i + 1;
                    end
                end
                if (pe_idx1 != -1) begin
                    pe_state_d[pe_idx1] = 1'b1;
                    pe_timer_d[pe_idx1] = cycles_to_run_l;
                    pe_state_d[pe_idx2] = 1'b1;
                    pe_timer_d[pe_idx2] = cycles_to_run_l;
                    island_accepted_d = 1'b1;
                    $display("[%0t] Controller: Allocated latched island size %0d to PE pair %0d-%0d (Enhanced). Penalty: %0d",
                             $time, latched_island_size, pe_idx1, pe_idx2, latched_needs_penalty);
                end
            end

            if (!island_accepted_d && (latched_island_size <= C_MAX)) begin
                pe_idx = -1;
                for (i = 0; i < NUM_PES; i = i + 1) begin
                    if (pe_state_q[i] == 1'b0 && pe_idx == -1) begin
                        pe_idx = i;
                    end
                end
                if (pe_idx != -1) begin
                    pe_state_d[pe_idx] = 1'b1;
                    pe_timer_d[pe_idx] = cycles_to_run_l;
                    island_accepted_d = 1'b1;
                    $display("[%0t] Controller: Allocated latched island size %0d to PE %0d. Penalty: %0d",
                             $time, latched_island_size, pe_idx, latched_needs_penalty);
                end
            end

            if (island_accepted_d) begin
                controller_state_d = 1'b0;
            end else begin
                controller_state_d = 1'b1;
            end

        end else begin
            // no request: stay idle
            controller_state_d = controller_state_q;
            island_accepted_d = 1'b0;
        end
    end

    // register and expose island_accepted
    assign island_accepted = island_accepted_q;

    // processing_done: detect transition busy->idle with controller idle
    reg busy_last_cycle_q;
    always @(posedge clk or negedge rst_n) begin
        if (!rst_n) busy_last_cycle_q <= 1'b0;
        else busy_last_cycle_q <= (|pe_state_q);
    end

    assign processing_done = busy_last_cycle_q && !(|pe_state_q) && (controller_state_q == 1'b0);
    assign accelerator_busy = (|pe_state_q);

endmodule

hardware/tb_igcn_accelerator.sv
//=====================================================================
// tb_igcn_accelerator.sv  -- Icarus-compatible testbench
//=====================================================================
`timescale 1ns / 1ps

module tb_igcn_accelerator;

    // Parameters (match DUT)
    localparam integer NUM_PES = 4;
    localparam integer C_MAX = 32;
    localparam integer PE_COMPUTE_CYCLES = 100;
    localparam integer FRAGMENTATION_PENALTY_CYCLES = 50;

    // Signals
    reg clk = 0;
    reg rst_n;
    reg start_processing;
    reg [15:0] island_size;
    reg strategy_is_enhanced;
    reg island_needs_penalty;
    wire island_accepted;
    wire accelerator_busy;
    wire processing_done;

    // Instantiate DUT (explicit port mapping)
    igcn_accelerator #(
        .NUM_PES(NUM_PES),
        .C_MAX(C_MAX),
        .PE_COMPUTE_CYCLES(PE_COMPUTE_CYCLES),
        .FRAGMENTATION_PENALTY_CYCLES(FRAGMENTATION_PENALTY_CYCLES)
    ) dut (
        .clk(clk),
        .rst_n(rst_n),
        .start_processing(start_processing),
        .island_size(island_size),
        .strategy_is_enhanced(strategy_is_enhanced),
        .island_needs_penalty(island_needs_penalty),
        .island_accepted(island_accepted),
        .accelerator_busy(accelerator_busy),
        .processing_done(processing_done)
    );

    // Clock generation: 10ns period
    always #5 clk = ~clk;

    // Helper tasks
    task reset_dut();
        begin
            rst_n = 1'b0;
            start_processing = 1'b0;
            island_size = 16'h0;
            strategy_is_enhanced = 1'b0;
            island_needs_penalty = 1'b0;
            #20;
            rst_n = 1'b1;
            #10;
            $display("[%0t] TB: Reset complete.", $time);
        end
    endtask

    task submit_island_chunk(input integer size, input bit strategy_enh, input bit needs_penalty);
        begin
            @(posedge clk);
            strategy_is_enhanced = strategy_enh;
            island_size = size;
            island_needs_penalty = needs_penalty;
            start_processing = 1'b1;
            @(posedge clk); // hold one cycle
            start_processing = 1'b0;

            // wait for registered acceptance pulse
            wait (island_accepted == 1'b1);
            $display("[%0t] TB: Accelerator accepted island size=%0d (penalty=%0d, strategy=%s)",
                     $time, size, needs_penalty, strategy_enh ? "Enhanced" : "Baseline");
            @(posedge clk); // ensure acceptance pulse cleared
        end
    endtask

    // Main test
    initial begin
        integer island_sizes[0:4];
        integer i;
        longint baseline_start, baseline_end, enhanced_start, enhanced_end;

        // populate island sizes (example set)
        island_sizes[0] = C_MAX / 2;
        island_sizes[1] = C_MAX - 5;
        island_sizes[2] = C_MAX + 10;
        island_sizes[3] = (C_MAX * 18) / 10; // ~1.8 * C_MAX
        island_sizes[4] = (C_MAX * 25) / 10; // ~2.5 * C_MAX

        $display("CONFIG: NUM_PES=%0d C_MAX=%0d", NUM_PES, C_MAX);

        $dumpfile("igcn_tb.vcd");
        $dumpvars(0, tb_igcn_accelerator);

        // Baseline test
        reset_dut();
        $display("\n--- Baseline Strategy ---");
        strategy_is_enhanced = 1'b0;
        baseline_start = $time;

        for (i = 0; i < 5; i = i + 1) begin
            integer raw;
            raw = island_sizes[i];
            if (raw <= C_MAX) begin
                submit_island_chunk(raw, 1'b0, 1'b0);
            end else begin
                integer rem;
                rem = raw;
                while (rem > 0) begin
                    integer chunk;
                    if (rem > C_MAX) chunk = C_MAX; else chunk = rem;
                    submit_island_chunk(chunk, 1'b0, 1'b1);
                    rem = rem - chunk;
                end
            end
        end

        // wait for completion
        wait (processing_done == 1'b1);
        baseline_end = $time;
        $display("[%0t] TB: Baseline finished. cycles=%0d", $time, (baseline_end - baseline_start)/10);

        // Enhanced test
        #50;
        reset_dut();
        $display("\n--- Enhanced Strategy ---");
        strategy_is_enhanced = 1'b1;
        enhanced_start = $time;

        for (i = 0; i < 5; i = i + 1) begin
            integer raw;
            raw = island_sizes[i];
            if (raw <= (2*C_MAX) && NUM_PES >= 2) begin
                submit_island_chunk(raw, 1'b1, 1'b0);
            end else begin
                integer rem;
                rem = raw;
                while (rem > 0) begin
                    integer chunk;
                    if (rem > (2*C_MAX)) chunk = 2*C_MAX; else chunk = rem;
                    submit_island_chunk(chunk, 1'b1, 1'b1);
                    rem = rem - chunk;
                end
            end
        end

        wait (processing_done == 1'b1);
        enhanced_end = $time;
        $display("[%0t] TB: Enhanced finished. cycles=%0d", $time, (enhanced_end - enhanced_start)/10);

        // summary
        $display("\n--- Results ---");
        $display("Baseline cycles: %0d", (baseline_end - baseline_start)/10);
        $display("Enhanced cycles: %0d", (enhanced_end - enhanced_start)/10);
        if ((enhanced_end - enhanced_start) > 0) begin
            real speedup;
            speedup = real'(baseline_end - baseline_start) / real'(enhanced_end - enhanced_start);
            $display("Speedup: %.2fx", speedup);
        end

        #50;
        $finish;
    end

endmodule

hardware/igcn_tb.vcd
$date
	Wed Oct 22 01:05:08 2025
$end
$version
	Icarus Verilog
$end
$timescale
	1ps
$end
$scope module tb_igcn_accelerator $end
$var wire 1 ! processing_done $end
$var wire 1 " island_accepted $end
$var wire 1 # accelerator_busy $end
$var parameter 32 $ C_MAX $end
$var parameter 32 % FRAGMENTATION_PENALTY_CYCLES $end
$var parameter 32 & NUM_PES $end
$var parameter 32 ' PE_COMPUTE_CYCLES $end
$var reg 1 ( clk $end
$var reg 1 ) island_needs_penalty $end
$var reg 16 * island_size [15:0] $end
$var reg 1 + rst_n $end
$var reg 1 , start_processing $end
$var reg 1 - strategy_is_enhanced $end
$scope module dut $end
$var wire 1 ( clk $end
$var wire 1 " island_accepted $end
$var wire 1 ) island_needs_penalty $end
$var wire 16 . island_size [15:0] $end
$var wire 1 ! processing_done $end
$var wire 1 + rst_n $end
$var wire 1 , start_processing $end
$var wire 1 - strategy_is_enhanced $end
$var wire 1 # accelerator_busy $end
$var parameter 32 / C_MAX $end
$var parameter 32 0 FRAGMENTATION_PENALTY_CYCLES $end
$var parameter 32 1 NUM_PES $end
$var parameter 32 2 PE_COMPUTE_CYCLES $end
$var reg 1 3 busy_last_cycle_q $end
$var reg 1 4 controller_state_d $end
$var reg 1 5 controller_state_q $end
$var reg 1 6 island_accepted_d $end
$var reg 1 7 island_accepted_q $end
$var reg 16 8 latched_island_size [15:0] $end
$var reg 1 9 latched_needs_penalty $end
$var reg 1 : latched_strategy $end
$var reg 4 ; pe_state_d [3:0] $end
$var reg 4 < pe_state_q [3:0] $end
$var integer 32 = cycles_to_run [31:0] $end
$var integer 32 > cycles_to_run_l [31:0] $end
$var integer 32 ? i [31:0] $end
$var integer 32 @ pe_idx [31:0] $end
$var integer 32 A pe_idx1 [31:0] $end
$var integer 32 B pe_idx2 [31:0] $end
$upscope $end
$scope begin $unm_blk_40 $end
$var reg 64 C baseline_end [63:0] $end
$var reg 64 D baseline_start [63:0] $end
$var reg 64 E enhanced_end [63:0] $end
$var reg 64 F enhanced_start [63:0] $end
$var integer 32 G i [31:0] $end
$scope begin $unm_blk_41 $end
$var integer 32 H raw [31:0] $end
$scope begin $unm_blk_43 $end
$var integer 32 I rem [31:0] $end
$scope begin $unm_blk_44 $end
$var integer 32 J chunk [31:0] $end
$upscope $end
$upscope $end
$upscope $end
$scope begin $unm_blk_45 $end
$var integer 32 K raw [31:0] $end
$scope begin $unm_blk_47 $end
$var integer 32 L rem [31:0] $end
$scope begin $unm_blk_48 $end
$var integer 32 M chunk [31:0] $end
$upscope $end
$upscope $end
$upscope $end
$scope begin $unm_blk_49 $end
$var real 1 N speedup $end
$upscope $end
$upscope $end
$scope task reset_dut $end
$upscope $end
$scope task submit_island_chunk $end
$var reg 1 O needs_penalty $end
$var integer 32 P size [31:0] $end
$var reg 1 Q strategy_enh $end
$upscope $end
$upscope $end
$enddefinitions $end
$comment Show the parameter values. $end
$dumpall
b1100100 2
b100 1
b110010 0
b100000 /
b1100100 '
b100 &
b110010 %
b100000 $
$end
#0
$dumpvars
0Q
bx P
0O
r0 N
bx M
bx L
bx K
bx J
bx I
bx H
bx G
b0 F
b0 E
b0 D
b0 C
bx B
bx A
bx @
b100 ?
bx >
bx =
b0 <
b0 ;
0:
09
b0 8
07
06
05
04
03
b0 .
0-
0,
0+
b0 *
0)
0(
0#
0"
0!
$end
#5000
b100 ?
1(
#10000
0(
#15000
b100 ?
1(
#20000
0(
1+
#25000
b100 ?
1(
#30000
0(
b10000 P
b10000 H
b0 G
b11110 D
#35000
b10000 8
16
b1 ;
b0 @
b11111111111111111111111111111111 B
b11111111111111111111111111111111 A
b1100100 =
b100 ?
1,
b10000 *
b10000 .
1(
#40000
0(
#45000
1"
17
1#
b1 <
06
b1 ;
b100 ?
0,
1(
#50000
0(
#55000
0"
07
13
b100 ?
b11011 P
b11011 H
b1 G
1(
#60000
0(
#65000
b11011 8
16
b11 ;
b1 @
b100 ?
1,
b11011 *
b11011 .
1(
#70000
0(
#75000
1"
17
b11 <
06
b11 ;
b100 ?
0,
1(
#80000
0(
#85000
0"
07
b100 ?
1O
b100000 P
b100000 J
b101010 I
b101010 H
b10 G
1(
#90000
0(
#95000
19
b100000 8
16
b111 ;
b10 @
b10010110 =
b100 ?
1,
1)
b100000 *
b100000 .
1(
#100000
0(
#105000
1"
17
b111 <
06
b111 ;
b100 ?
0,
1(
#110000
0(
#115000
0"
07
b100 ?
b1010 P
b1010 J
b1010 I
1(
#120000
0(
#125000
b1010 8
16
b1111 ;
b11 @
b100 ?
1,
b1010 *
b1010 .
1(
#130000
0(
#135000
1"
17
b1111 <
06
b1111 ;
b100 ?
0,
1(
#140000
0(
#145000
0"
07
b100 ?
b100000 P
b100000 J
b111001 H
b11 G
b111001 I
1(
#150000
0(
#155000
b100000 8
14
b11111111111111111111111111111111 @
b100 ?
1,
b100000 *
b100000 .
1(
#160000
0(
#165000
b10010110 >
15
14
b100 ?
0,
1(
#170000
0(
#175000
b100 ?
1(
#180000
0(
#185000
b100 ?
1(
#190000
0(
#195000
b100 ?
1(
#200000
0(
#205000
b100 ?
1(
#210000
0(
#215000
b100 ?
1(
#220000
0(
#225000
b100 ?
1(
#230000
0(
#235000
b100 ?
1(
#240000
0(
#245000
b100 ?
1(
#250000
0(
#255000
b100 ?
1(
#260000
0(
#265000
b100 ?
1(
#270000
0(
#275000
b100 ?
1(
#280000
0(
#285000
b100 ?
1(
#290000
0(
#295000
b100 ?
1(
#300000
0(
#305000
b100 ?
1(
#310000
0(
#315000
b100 ?
1(
#320000
0(
#325000
b100 ?
1(
#330000
0(
#335000
b100 ?
1(
#340000
0(
#345000
b100 ?
1(
#350000
0(
#355000
b100 ?
1(
#360000
0(
#365000
b100 ?
1(
#370000
0(
#375000
b100 ?
1(
#380000
0(
#385000
b100 ?
1(
#390000
0(
#395000
b100 ?
1(
#400000
0(
#405000
b100 ?
1(
#410000
0(
#415000
b100 ?
1(
#420000
0(
#425000
b100 ?
1(
#430000
0(
#435000
b100 ?
1(
#440000
0(
#445000
b100 ?
1(
#450000
0(
#455000
b100 ?
1(
#460000
0(
#465000
b100 ?
1(
#470000
0(
#475000
b100 ?
1(
#480000
0(
#485000
b100 ?
1(
#490000
0(
#495000
b100 ?
1(
#500000
0(
#505000
b100 ?
1(
#510000
0(
#515000
b100 ?
1(
#520000
0(
#525000
b100 ?
1(
#530000
0(
#535000
b100 ?
1(
#540000
0(
#545000
b100 ?
1(
#550000
0(
#555000
b100 ?
1(
#560000
0(
#565000
b100 ?
1(
#570000
0(
#575000
b100 ?
1(
#580000
0(
#585000
b100 ?
1(
#590000
0(
#595000
b100 ?
1(
#600000
0(
#605000
b100 ?
1(
#610000
0(
#615000
b100 ?
1(
#620000
0(
#625000
b100 ?
1(
#630000
0(
#635000
b100 ?
1(
#640000
0(
#645000
b100 ?
1(
#650000
0(
#655000
b100 ?
1(
#660000
0(
#665000
b100 ?
1(
#670000
0(
#675000
b100 ?
1(
#680000
0(
#685000
b100 ?
1(
#690000
0(
#695000
b100 ?
1(
#700000
0(
#705000
b100 ?
1(
#710000
0(
#715000
b100 ?
1(
#720000
0(
#725000
b100 ?
1(
#730000
0(
#735000
b100 ?
1(
#740000
0(
#745000
b100 ?
1(
#750000
0(
#755000
b100 ?
1(
#760000
0(
#765000
b100 ?
1(
#770000
0(
#775000
b100 ?
1(
#780000
0(
#785000
b100 ?
1(
#790000
0(
#795000
b100 ?
1(
#800000
0(
#805000
b100 ?
1(
#810000
0(
#815000
b100 ?
1(
#820000
0(
#825000
b100 ?
1(
#830000
0(
#835000
b100 ?
1(
#840000
0(
#845000
b100 ?
1(
#850000
0(
#855000
b100 ?
1(
#860000
0(
#865000
b100 ?
1(
#870000
0(
#875000
b100 ?
1(
#880000
0(
#885000
b100 ?
1(
#890000
0(
#895000
b100 ?
1(
#900000
0(
#905000
b100 ?
1(
#910000
0(
#915000
b100 ?
1(
#920000
0(
#925000
b100 ?
1(
#930000
0(
#935000
b100 ?
1(
#940000
0(
#945000
b100 ?
1(
#950000
0(
#955000
b100 ?
1(
#960000
0(
#965000
b100 ?
1(
#970000
0(
#975000
b100 ?
1(
#980000
0(
#985000
b100 ?
1(
#990000
0(
#995000
b100 ?
1(
#1000000
0(
#1005000
b100 ?
1(
#1010000
0(
#1015000
b100 ?
1(
#1020000
0(
#1025000
b100 ?
1(
#1030000
0(
#1035000
b1110 ;
b100 ?
1(
#1040000
0(
#1045000
04
16
b1111 ;
b0 @
b1110 <
b100 ?
1(
#1050000
0(
#1055000
06
1"
17
05
b1111 <
b100 ?
1(
#1060000
0(
#1065000
b1101 ;
0"
07
b100 ?
b11001 P
b11001 J
b11001 I
1(
#1070000
0(
#1075000
16
b1111 ;
b11001 8
b1101 <
04
b1 @
b100 ?
1,
b11001 *
b11001 .
1(
#1080000
0(
#1085000
1"
17
b1111 <
06
b1111 ;
b100 ?
0,
1(
#1090000
0(
#1095000
0"
07
b100 ?
b100000 P
b100000 J
b1010000 H
b100 G
b1010000 I
1(
#1100000
0(
#1105000
b100000 8
14
b11111111111111111111111111111111 @
b100 ?
1,
b100000 *
b100000 .
1(
#1110000
0(
#1115000
15
14
b100 ?
0,
1(
#1120000
0(
#1125000
b100 ?
1(
#1130000
0(
#1135000
b100 ?
1(
#1140000
0(
#1145000
b100 ?
1(
#1150000
0(
#1155000
b100 ?
1(
#1160000
0(
#1165000
b100 ?
1(
#1170000
0(
#1175000
b100 ?
1(
#1180000
0(
#1185000
b100 ?
1(
#1190000
0(
#1195000
b100 ?
1(
#1200000
0(
#1205000
b100 ?
1(
#1210000
0(
#1215000
b100 ?
1(
#1220000
0(
#1225000
b100 ?
1(
#1230000
0(
#1235000
b100 ?
1(
#1240000
0(
#1245000
b100 ?
1(
#1250000
0(
#1255000
b100 ?
1(
#1260000
0(
#1265000
b100 ?
1(
#1270000
0(
#1275000
b100 ?
1(
#1280000
0(
#1285000
b100 ?
1(
#1290000
0(
#1295000
b100 ?
1(
#1300000
0(
#1305000
b100 ?
1(
#1310000
0(
#1315000
b100 ?
1(
#1320000
0(
#1325000
b100 ?
1(
#1330000
0(
#1335000
b100 ?
1(
#1340000
0(
#1345000
b100 ?
1(
#1350000
0(
#1355000
b100 ?
1(
#1360000
0(
#1365000
b100 ?
1(
#1370000
0(
#1375000
b100 ?
1(
#1380000
0(
#1385000
b100 ?
1(
#1390000
0(
#1395000
b100 ?
1(
#1400000
0(
#1405000
b100 ?
1(
#1410000
0(
#1415000
b100 ?
1(
#1420000
0(
#1425000
b100 ?
1(
#1430000
0(
#1435000
b100 ?
1(
#1440000
0(
#1445000
b100 ?
1(
#1450000
0(
#1455000
b100 ?
1(
#1460000
0(
#1465000
b100 ?
1(
#1470000
0(
#1475000
b100 ?
1(
#1480000
0(
#1485000
b100 ?
1(
#1490000
0(
#1495000
b100 ?
1(
#1500000
0(
#1505000
b100 ?
1(
#1510000
0(
#1515000
b100 ?
1(
#1520000
0(
#1525000
b100 ?
1(
#1530000
0(
#1535000
b100 ?
1(
#1540000
0(
#1545000
b100 ?
1(
#1550000
0(
#1555000
b100 ?
1(
#1560000
0(
#1565000
b100 ?
1(
#1570000
0(
#1575000
b100 ?
1(
#1580000
0(
#1585000
b100 ?
1(
#1590000
0(
#1595000
b1011 ;
b100 ?
1(
#1600000
0(
#1605000
04
16
b1111 ;
b10 @
b1011 <
b100 ?
1(
#1610000
0(
#1615000
06
1"
17
05
b1111 <
b100 ?
1(
#1620000
0(
#1625000
b111 ;
0"
07
b100 ?
b110000 I
1(
#1630000
0(
#1635000
16
b1111 ;
b111 <
04
b11 @
b100 ?
1,
1(
#1640000
0(
#1645000
1"
17
b1111 <
06
b1111 ;
b100 ?
0,
1(
#1650000
0(
#1655000
0"
07
b100 ?
b10000 P
b10000 J
b10000 I
1(
#1660000
0(
#1665000
b10000 8
14
b11111111111111111111111111111111 @
b100 ?
1,
b10000 *
b10000 .
1(
#1670000
0(
#1675000
15
14
b100 ?
0,
1(
#1680000
0(
#1685000
b100 ?
1(
#1690000
0(
#1695000
b100 ?
1(
#1700000
0(
#1705000
b100 ?
1(
#1710000
0(
#1715000
b100 ?
1(
#1720000
0(
#1725000
b100 ?
1(
#1730000
0(
#1735000
b100 ?
1(
#1740000
0(
#1745000
b100 ?
1(
#1750000
0(
#1755000
b100 ?
1(
#1760000
0(
#1765000
b100 ?
1(
#1770000
0(
#1775000
b100 ?
1(
#1780000
0(
#1785000
b100 ?
1(
#1790000
0(
#1795000
b100 ?
1(
#1800000
0(
#1805000
b100 ?
1(
#1810000
0(
#1815000
b100 ?
1(
#1820000
0(
#1825000
b100 ?
1(
#1830000
0(
#1835000
b100 ?
1(
#1840000
0(
#1845000
b100 ?
1(
#1850000
0(
#1855000
b100 ?
1(
#1860000
0(
#1865000
b100 ?
1(
#1870000
0(
#1875000
b100 ?
1(
#1880000
0(
#1885000
b100 ?
1(
#1890000
0(
#1895000
b100 ?
1(
#1900000
0(
#1905000
b100 ?
1(
#1910000
0(
#1915000
b100 ?
1(
#1920000
0(
#1925000
b100 ?
1(
#1930000
0(
#1935000
b100 ?
1(
#1940000
0(
#1945000
b100 ?
1(
#1950000
0(
#1955000
b100 ?
1(
#1960000
0(
#1965000
b100 ?
1(
#1970000
0(
#1975000
b100 ?
1(
#1980000
0(
#1985000
b100 ?
1(
#1990000
0(
#1995000
b100 ?
1(
#2000000
0(
#2005000
b100 ?
1(
#2010000
0(
#2015000
b100 ?
1(
#2020000
0(
#2025000
b100 ?
1(
#2030000
0(
#2035000
b100 ?
1(
#2040000
0(
#2045000
b100 ?
1(
#2050000
0(
#2055000
b100 ?
1(
#2060000
0(
#2065000
b100 ?
1(
#2070000
0(
#2075000
b100 ?
1(
#2080000
0(
#2085000
b100 ?
1(
#2090000
0(
#2095000
b100 ?
1(
#2100000
0(
#2105000
b100 ?
1(
#2110000
0(
#2115000
b100 ?
1(
#2120000
0(
#2125000
b100 ?
1(
#2130000
0(
#2135000
b100 ?
1(
#2140000
0(
#2145000
b100 ?
1(
#2150000
0(
#2155000
b100 ?
1(
#2160000
0(
#2165000
b100 ?
1(
#2170000
0(
#2175000
b100 ?
1(
#2180000
0(
#2185000
b100 ?
1(
#2190000
0(
#2195000
b100 ?
1(
#2200000
0(
#2205000
b100 ?
1(
#2210000
0(
#2215000
b100 ?
1(
#2220000
0(
#2225000
b100 ?
1(
#2230000
0(
#2235000
b100 ?
1(
#2240000
0(
#2245000
b100 ?
1(
#2250000
0(
#2255000
b100 ?
1(
#2260000
0(
#2265000
b100 ?
1(
#2270000
0(
#2275000
b100 ?
1(
#2280000
0(
#2285000
b100 ?
1(
#2290000
0(
#2295000
b100 ?
1(
#2300000
0(
#2305000
b100 ?
1(
#2310000
0(
#2315000
b100 ?
1(
#2320000
0(
#2325000
b100 ?
1(
#2330000
0(
#2335000
b100 ?
1(
#2340000
0(
#2345000
b100 ?
1(
#2350000
0(
#2355000
b100 ?
1(
#2360000
0(
#2365000
b100 ?
1(
#2370000
0(
#2375000
b100 ?
1(
#2380000
0(
#2385000
b100 ?
1(
#2390000
0(
#2395000
b100 ?
1(
#2400000
0(
#2405000
b100 ?
1(
#2410000
0(
#2415000
b100 ?
1(
#2420000
0(
#2425000
b100 ?
1(
#2430000
0(
#2435000
b100 ?
1(
#2440000
0(
#2445000
b100 ?
1(
#2450000
0(
#2455000
b100 ?
1(
#2460000
0(
#2465000
b100 ?
1(
#2470000
0(
#2475000
b100 ?
1(
#2480000
0(
#2485000
b100 ?
1(
#2490000
0(
#2495000
b100 ?
1(
#2500000
0(
#2505000
b100 ?
1(
#2510000
0(
#2515000
b100 ?
1(
#2520000
0(
#2525000
b100 ?
1(
#2530000
0(
#2535000
b100 ?
1(
#2540000
0(
#2545000
b1110 ;
b100 ?
1(
#2550000
0(
#2555000
04
16
b1111 ;
b0 @
b1110 <
b100 ?
1(
#2560000
0(
#2565000
06
1"
17
05
b1111 <
b100 ?
1(
#2570000
0(
#2575000
b1101 ;
0"
07
b100 ?
b101 G
b0 I
1(
#2580000
0(
#2585000
b1101 <
b100 ?
1(
#2590000
0(
#2595000
b100 ?
1(
#2600000
0(
#2605000
b100 ?
1(
#2610000
0(
#2615000
b100 ?
1(
#2620000
0(
#2625000
b100 ?
1(
#2630000
0(
#2635000
b100 ?
1(
#2640000
0(
#2645000
b100 ?
1(
#2650000
0(
#2655000
b100 ?
1(
#2660000
0(
#2665000
b100 ?
1(
#2670000
0(
#2675000
b100 ?
1(
#2680000
0(
#2685000
b100 ?
1(
#2690000
0(
#2695000
b100 ?
1(
#2700000
0(
#2705000
b100 ?
1(
#2710000
0(
#2715000
b100 ?
1(
#2720000
0(
#2725000
b100 ?
1(
#2730000
0(
#2735000
b100 ?
1(
#2740000
0(
#2745000
b100 ?
1(
#2750000
0(
#2755000
b100 ?
1(
#2760000
0(
#2765000
b100 ?
1(
#2770000
0(
#2775000
b100 ?
1(
#2780000
0(
#2785000
b100 ?
1(
#2790000
0(
#2795000
b100 ?
1(
#2800000
0(
#2805000
b100 ?
1(
#2810000
0(
#2815000
b100 ?
1(
#2820000
0(
#2825000
b100 ?
1(
#2830000
0(
#2835000
b100 ?
1(
#2840000
0(
#2845000
b100 ?
1(
#2850000
0(
#2855000
b100 ?
1(
#2860000
0(
#2865000
b100 ?
1(
#2870000
0(
#2875000
b100 ?
1(
#2880000
0(
#2885000
b100 ?
1(
#2890000
0(
#2895000
b100 ?
1(
#2900000
0(
